{
    "base_branch": "CMSSW_11_1_X", 
    "release_name": "CMSSW_11_1_ROOT6_X", 
    "comparisons": [
        {
            "comp_baseline_state": "errors", 
            "python3_tests": [], 
            "tests_archs": [], 
            "cmsdist_merged_prs": {
                "slc7_amd64_gcc820": [
                    {
                        "hash": "691a3aee46156f10d23a3d2e746f0d35a65e2b65", 
                        "title": "create single crab to deploy helper scripts", 
                        "url": "https://github.com/cms-sw/cmsdist/pull/5473", 
                        "number": "5473", 
                        "is_merge_commit": false, 
                        "from_merge_commit": true, 
                        "author_login": "cms-sw"
                    }
                ]
            }, 
            "cmsdist_compared_tags": {
                "slc7_amd64_gcc820": "IB/CMSSW_11_1_ROOT6_X_2020-01-15-2300/slc7_amd64_gcc820..IB/CMSSW_11_1_X/rootmaster"
            }, 
            "cmsdistTags": {}, 
            "next_ib": true, 
            "RVExceptions": null, 
            "igprof": "not-found", 
            "base_branch": "CMSSW_11_1_X", 
            "compared_tags": "CMSSW_11_1_ROOT6_X_2020-01-17-2300-->CMSSW_11_1_X", 
            "dqm_tests": "inprogress", 
            "utests": [], 
            "ib_date": "2020-01-17-2300-0001", 
            "relvals": [], 
            "release_queue": "CMSSW_11_1_ROOT6_X", 
            "release_name": "CMSSW_11_1_X", 
            "comp_baseline": "not-found", 
            "gpu_utests": [], 
            "material_budget_comparison": "not-found", 
            "merged_prs": [], 
            "fwlite": [], 
            "invalid_includes": [], 
            "builds": [], 
            "material_budget_v2": "not-found", 
            "static_checks_v2": "not-found", 
            "valgrind": "not-found", 
            "material_budget": "not-found", 
            "dupDict": [], 
            "static_checks_failures": "not-found", 
            "static_checks": "not-found", 
            "isIB": false, 
            "inProgress": false, 
            "addons": [], 
            "hlt_tests": "not-found"
        }, 
        {
            "comp_baseline_state": "errors", 
            "python3_tests": [], 
            "tests_archs": [
                "slc7_amd64_gcc820"
            ], 
            "cmsdist_merged_prs": {
                "slc7_amd64_gcc820": []
            }, 
            "cmsdist_compared_tags": {
                "slc7_amd64_gcc820": "IB/CMSSW_11_1_ROOT6_X_2020-01-15-2300/slc7_amd64_gcc820..IB/CMSSW_11_1_ROOT6_X_2020-01-15-2300/slc7_amd64_gcc820"
            }, 
            "cmsdistTags": {
                "slc7_amd64_gcc820": "IB/CMSSW_11_1_ROOT6_X_2020-01-15-2300/slc7_amd64_gcc820"
            }, 
            "next_ib": false, 
            "RVExceptions": null, 
            "igprof": "not-found", 
            "base_branch": "CMSSW_11_1_X", 
            "compared_tags": "CMSSW_11_1_ROOT6_X_2020-01-16-2300-->CMSSW_11_1_ROOT6_X_2020-01-17-2300", 
            "dqm_tests": "inprogress", 
            "utests": [
                {
                    "arch": "slc7_amd64_gcc820", 
                    "passed": "passed", 
                    "file": "/data/sdt/buildlogs/slc7_amd64_gcc820/www/fri/11.1.ROOT6-fri-23/CMSSW_11_1_ROOT6_X_2020-01-17-2300/unitTests-summary.log", 
                    "details": {
                        "num_fails": "0"
                    }
                }
            ], 
            "ib_date": "2020-01-17-2300-0000", 
            "relvals": [
                {
                    "done": true, 
                    "arch": "slc7_amd64_gcc820", 
                    "passed": false, 
                    "file": "/data/sdt/buildlogs/slc7_amd64_gcc820/www/fri/11.1.ROOT6-fri-23/CMSSW_11_1_ROOT6_X_2020-01-17-2300/pyRelValMatrixLogs/run/runall-report-step123-.log", 
                    "details": {
                        "num_passed": 3164, 
                        "known_failed": 0, 
                        "num_failed": 1
                    }
                }
            ], 
            "release_queue": "CMSSW_11_1_ROOT6_X", 
            "release_name": "CMSSW_11_1_ROOT6_X_2020-01-17-2300", 
            "comp_baseline": "not-found", 
            "gpu_utests": [], 
            "material_budget_comparison": "not-found", 
            "merged_prs": [
                {
                    "hash": "0deef1bd925b4e94cbbb560cada9c5fe9d67c72e", 
                    "title": "Utilities/StaticAnalysers: Unregister unused getParamDumper checker ", 
                    "url": "https://github.com/cms-sw/cmssw/pull/28744", 
                    "number": "28744", 
                    "is_merge_commit": false, 
                    "from_merge_commit": false, 
                    "author_login": "gartung"
                }, 
                {
                    "hash": "f326b4d6d8624c3e2bfe4d2e5504ff2590c43a9c", 
                    "title": "PPS: faster proton reconstruction", 
                    "url": "https://github.com/cms-sw/cmssw/pull/28738", 
                    "number": "28738", 
                    "is_merge_commit": false, 
                    "from_merge_commit": false, 
                    "author_login": "CTPPS"
                }, 
                {
                    "hash": "7bcaeda038c3db04a69c2413244e777bf7749ba4", 
                    "title": "Bugfix: Crash in DaqTestHistograms", 
                    "url": "https://github.com/cms-sw/cmssw/pull/28751", 
                    "number": "28751", 
                    "is_merge_commit": false, 
                    "from_merge_commit": false, 
                    "author_login": "smorovic"
                }, 
                {
                    "hash": "76d423b01ffe69247c04ae7de79172201d58b118", 
                    "title": "Replace tbb::tbb_hash and tbb::tbb_hasher with std::hash", 
                    "url": "https://github.com/cms-sw/cmssw/pull/28750", 
                    "number": "28750", 
                    "is_merge_commit": false, 
                    "from_merge_commit": false, 
                    "author_login": "guitargeek"
                }
            ], 
            "fwlite": [], 
            "invalid_includes": [], 
            "builds": [
                {
                    "arch": "slc7_amd64_gcc820", 
                    "passed": "passed", 
                    "file": "/data/sdt/buildlogs/slc7_amd64_gcc820/www/fri/11.1.ROOT6-fri-23/CMSSW_11_1_ROOT6_X_2020-01-17-2300/new/logAnalysis.pkl", 
                    "details": {
                        "ignoreWarning": 76
                    }
                }
            ], 
            "material_budget_v2": "not-found", 
            "static_checks_v2": "not-found", 
            "valgrind": "not-found", 
            "material_budget": "not-found", 
            "dupDict": [
                {
                    "arch": "slc7_amd64_gcc820", 
                    "passed": "passed"
                }
            ], 
            "static_checks_failures": "not-found", 
            "static_checks": "not-found", 
            "isIB": true, 
            "inProgress": false, 
            "addons": [
                {
                    "arch": "slc7_amd64_gcc820", 
                    "passed": true, 
                    "file": "/data/sdt/buildlogs/slc7_amd64_gcc820/www/fri/11.1.ROOT6-fri-23/CMSSW_11_1_ROOT6_X_2020-01-17-2300/addOnTests.log", 
                    "details": {}
                }
            ], 
            "hlt_tests": "not-found"
        }, 
        {
            "comp_baseline_state": "errors", 
            "python3_tests": [], 
            "tests_archs": [
                "slc7_amd64_gcc820"
            ], 
            "cmsdist_merged_prs": {
                "slc7_amd64_gcc820": []
            }, 
            "cmsdist_compared_tags": {
                "slc7_amd64_gcc820": "IB/CMSSW_11_1_ROOT6_X_2020-01-15-2300/slc7_amd64_gcc820..IB/CMSSW_11_1_ROOT6_X_2020-01-15-2300/slc7_amd64_gcc820"
            }, 
            "cmsdistTags": {
                "slc7_amd64_gcc820": "IB/CMSSW_11_1_ROOT6_X_2020-01-15-2300/slc7_amd64_gcc820"
            }, 
            "next_ib": false, 
            "RVExceptions": null, 
            "igprof": "not-found", 
            "base_branch": "CMSSW_11_1_X", 
            "compared_tags": "CMSSW_11_1_ROOT6_X_2020-01-15-2300-->CMSSW_11_1_ROOT6_X_2020-01-16-2300", 
            "dqm_tests": "inprogress", 
            "utests": [
                {
                    "arch": "slc7_amd64_gcc820", 
                    "passed": "failed", 
                    "file": "/data/sdt/buildlogs/slc7_amd64_gcc820/www/thu/11.1.ROOT6-thu-23/CMSSW_11_1_ROOT6_X_2020-01-16-2300/unitTests-summary.log", 
                    "details": {
                        "num_fails": "1"
                    }
                }
            ], 
            "ib_date": "2020-01-16-2300-0000", 
            "relvals": [
                {
                    "done": true, 
                    "arch": "slc7_amd64_gcc820", 
                    "passed": false, 
                    "file": "/data/sdt/buildlogs/slc7_amd64_gcc820/www/thu/11.1.ROOT6-thu-23/CMSSW_11_1_ROOT6_X_2020-01-16-2300/pyRelValMatrixLogs/run/runall-report-step123-.log", 
                    "details": {
                        "num_passed": 3164, 
                        "known_failed": 0, 
                        "num_failed": 1
                    }
                }
            ], 
            "release_queue": "CMSSW_11_1_ROOT6_X", 
            "release_name": "CMSSW_11_1_ROOT6_X_2020-01-16-2300", 
            "comp_baseline": "not-found", 
            "gpu_utests": [], 
            "material_budget_comparison": "not-found", 
            "merged_prs": [
                {
                    "hash": "b8d6745ee188904bce61732ed98f12c81de523a3", 
                    "title": "Removing unused variables from \"CTPPSPixelDQMSource.cc\" - fix suggested in PR #28726", 
                    "url": "https://github.com/cms-sw/cmssw/pull/28733", 
                    "number": "28733", 
                    "is_merge_commit": false, 
                    "from_merge_commit": false, 
                    "author_login": "AndreaBellora"
                }, 
                {
                    "hash": "e3ac83780c96fee7f4e7dcdf58925fe2b8428606", 
                    "title": "Clean dependencies for DataFormats/L1TMuon", 
                    "url": "https://github.com/cms-sw/cmssw/pull/28749", 
                    "number": "28749", 
                    "is_merge_commit": false, 
                    "from_merge_commit": false, 
                    "author_login": "guitargeek"
                }, 
                {
                    "hash": "8426162f4dba2b4161aae7ead03ede2ae7b06c46", 
                    "title": "PPS: DQM update", 
                    "url": "https://github.com/cms-sw/cmssw/pull/28742", 
                    "number": "28742", 
                    "is_merge_commit": false, 
                    "from_merge_commit": false, 
                    "author_login": "CTPPS"
                }, 
                {
                    "hash": "5b59a3575de07ab3da0371c50ebe1a0ec6127479", 
                    "title": "Declare SiTrackerMultiRecHit::cloneSH() to override", 
                    "url": "https://github.com/cms-sw/cmssw/pull/28743", 
                    "number": "28743", 
                    "is_merge_commit": false, 
                    "from_merge_commit": false, 
                    "author_login": "makortel"
                }
            ], 
            "fwlite": [], 
            "invalid_includes": [], 
            "builds": [
                {
                    "arch": "slc7_amd64_gcc820", 
                    "passed": "passed", 
                    "file": "/data/sdt/buildlogs/slc7_amd64_gcc820/www/thu/11.1.ROOT6-thu-23/CMSSW_11_1_ROOT6_X_2020-01-16-2300/new/logAnalysis.pkl", 
                    "details": {
                        "ignoreWarning": 14
                    }
                }
            ], 
            "material_budget_v2": "not-found", 
            "static_checks_v2": "not-found", 
            "valgrind": "not-found", 
            "material_budget": "not-found", 
            "dupDict": [
                {
                    "arch": "slc7_amd64_gcc820", 
                    "passed": "passed"
                }
            ], 
            "static_checks_failures": "not-found", 
            "static_checks": "not-found", 
            "isIB": true, 
            "inProgress": false, 
            "addons": [
                {
                    "arch": "slc7_amd64_gcc820", 
                    "passed": true, 
                    "file": "/data/sdt/buildlogs/slc7_amd64_gcc820/www/thu/11.1.ROOT6-thu-23/CMSSW_11_1_ROOT6_X_2020-01-16-2300/addOnTests.log", 
                    "details": {}
                }
            ], 
            "hlt_tests": "not-found"
        }, 
        {
            "comp_baseline_state": "errors", 
            "python3_tests": [], 
            "tests_archs": [
                "slc7_amd64_gcc820"
            ], 
            "cmsdist_merged_prs": {
                "slc7_amd64_gcc820": [
                    {
                        "hash": "bd0817fae8254f40f640a4201d1542204a8dfc3d", 
                        "title": "install crab in common; remove crab deps", 
                        "url": "https://github.com/cms-sw/cmsdist/pull/5466", 
                        "number": "5466", 
                        "is_merge_commit": false, 
                        "from_merge_commit": true, 
                        "author_login": "cms-sw"
                    }, 
                    {
                        "hash": "26b4163ad20c21bb07b7b9bc5c3602d16773530c", 
                        "title": "Updated root to tip of branch master", 
                        "url": "https://github.com/cms-sw/cmsdist/pull/5467", 
                        "number": "5467", 
                        "is_merge_commit": false, 
                        "from_merge_commit": false, 
                        "author_login": "smuzaffar"
                    }, 
                    {
                        "hash": "33ca9b8298de84866cc8343e064e8b9b8e7d7c82", 
                        "title": "Disable AVX2 for pytables", 
                        "url": "https://github.com/cms-sw/cmsdist/pull/5471", 
                        "number": "5471", 
                        "is_merge_commit": false, 
                        "from_merge_commit": true, 
                        "author_login": "cms-sw"
                    }
                ]
            }, 
            "cmsdist_compared_tags": {
                "slc7_amd64_gcc820": "IB/CMSSW_11_1_ROOT6_X_2020-01-14-2300/slc7_amd64_gcc820..IB/CMSSW_11_1_ROOT6_X_2020-01-15-2300/slc7_amd64_gcc820"
            }, 
            "cmsdistTags": {
                "slc7_amd64_gcc820": "IB/CMSSW_11_1_ROOT6_X_2020-01-15-2300/slc7_amd64_gcc820"
            }, 
            "next_ib": false, 
            "RVExceptions": null, 
            "igprof": "not-found", 
            "base_branch": "CMSSW_11_1_X", 
            "compared_tags": "CMSSW_11_1_ROOT6_X_2020-01-14-2300-->CMSSW_11_1_ROOT6_X_2020-01-15-2300", 
            "dqm_tests": "inprogress", 
            "utests": [
                {
                    "arch": "slc7_amd64_gcc820", 
                    "passed": "passed", 
                    "file": "/data/sdt/buildlogs/slc7_amd64_gcc820/www/wed/11.1.ROOT6-wed-23/CMSSW_11_1_ROOT6_X_2020-01-15-2300/unitTests-summary.log", 
                    "details": {
                        "num_fails": "0"
                    }
                }
            ], 
            "ib_date": "2020-01-15-2300-0000", 
            "relvals": [
                {
                    "done": true, 
                    "arch": "slc7_amd64_gcc820", 
                    "passed": false, 
                    "file": "/data/sdt/buildlogs/slc7_amd64_gcc820/www/wed/11.1.ROOT6-wed-23/CMSSW_11_1_ROOT6_X_2020-01-15-2300/pyRelValMatrixLogs/run/runall-report-step123-.log", 
                    "details": {
                        "num_passed": 3164, 
                        "known_failed": 0, 
                        "num_failed": 1
                    }
                }
            ], 
            "release_queue": "CMSSW_11_1_ROOT6_X", 
            "release_name": "CMSSW_11_1_ROOT6_X_2020-01-15-2300", 
            "comp_baseline": "not-found", 
            "gpu_utests": [], 
            "material_budget_comparison": "not-found", 
            "merged_prs": [
                {
                    "hash": "b4ebcd1821622801f32808481157d6eff3551de3", 
                    "title": "Reduce dependencies on RecoEgamma and requirements for RecoEgamma", 
                    "url": "https://github.com/cms-sw/cmssw/pull/28684", 
                    "number": "28684", 
                    "is_merge_commit": false, 
                    "from_merge_commit": false, 
                    "author_login": "guitargeek"
                }, 
                {
                    "hash": "57553401c56bd9417f87efe0c28a62e690e55ff1", 
                    "title": "Support of plot-specific input paramters for Payload Inspector", 
                    "url": "https://github.com/cms-sw/cmssw/pull/28648", 
                    "number": "28648", 
                    "is_merge_commit": false, 
                    "from_merge_commit": false, 
                    "author_login": "ggovi"
                }
            ], 
            "fwlite": [], 
            "invalid_includes": [], 
            "builds": [
                {
                    "arch": "slc7_amd64_gcc820", 
                    "passed": "passed", 
                    "file": "/data/sdt/buildlogs/slc7_amd64_gcc820/www/wed/11.1.ROOT6-wed-23/CMSSW_11_1_ROOT6_X_2020-01-15-2300/new/logAnalysis.pkl", 
                    "details": {
                        "ignoreWarning": 145
                    }
                }
            ], 
            "material_budget_v2": "not-found", 
            "static_checks_v2": "not-found", 
            "valgrind": "not-found", 
            "material_budget": "not-found", 
            "dupDict": [
                {
                    "arch": "slc7_amd64_gcc820", 
                    "passed": "passed"
                }
            ], 
            "static_checks_failures": "not-found", 
            "static_checks": "not-found", 
            "isIB": true, 
            "inProgress": false, 
            "addons": [
                {
                    "arch": "slc7_amd64_gcc820", 
                    "passed": true, 
                    "file": "/data/sdt/buildlogs/slc7_amd64_gcc820/www/wed/11.1.ROOT6-wed-23/CMSSW_11_1_ROOT6_X_2020-01-15-2300/addOnTests.log", 
                    "details": {}
                }
            ], 
            "hlt_tests": "not-found"
        }, 
        {
            "comp_baseline_state": "errors", 
            "python3_tests": [], 
            "tests_archs": [
                "slc7_amd64_gcc820"
            ], 
            "cmsdist_merged_prs": {
                "slc7_amd64_gcc820": []
            }, 
            "cmsdist_compared_tags": {
                "slc7_amd64_gcc820": "IB/CMSSW_11_1_ROOT6_X_2020-01-12-2300/slc7_amd64_gcc820..IB/CMSSW_11_1_ROOT6_X_2020-01-14-2300/slc7_amd64_gcc820"
            }, 
            "cmsdistTags": {
                "slc7_amd64_gcc820": "IB/CMSSW_11_1_ROOT6_X_2020-01-14-2300/slc7_amd64_gcc820"
            }, 
            "next_ib": false, 
            "RVExceptions": null, 
            "igprof": "not-found", 
            "base_branch": "CMSSW_11_1_X", 
            "compared_tags": "CMSSW_11_1_ROOT6_X_2020-01-13-2300-->CMSSW_11_1_ROOT6_X_2020-01-14-2300", 
            "dqm_tests": "inprogress", 
            "utests": [
                {
                    "arch": "slc7_amd64_gcc820", 
                    "passed": "passed", 
                    "file": "/data/sdt/buildlogs/slc7_amd64_gcc820/www/tue/11.1.ROOT6-tue-23/CMSSW_11_1_ROOT6_X_2020-01-14-2300/unitTests-summary.log", 
                    "details": {
                        "num_fails": "0"
                    }
                }
            ], 
            "ib_date": "2020-01-14-2300-0000", 
            "relvals": [
                {
                    "done": true, 
                    "arch": "slc7_amd64_gcc820", 
                    "passed": false, 
                    "file": "/data/sdt/buildlogs/slc7_amd64_gcc820/www/tue/11.1.ROOT6-tue-23/CMSSW_11_1_ROOT6_X_2020-01-14-2300/pyRelValMatrixLogs/run/runall-report-step123-.log", 
                    "details": {
                        "num_passed": 3164, 
                        "known_failed": 0, 
                        "num_failed": 1
                    }
                }
            ], 
            "release_queue": "CMSSW_11_1_ROOT6_X", 
            "release_name": "CMSSW_11_1_ROOT6_X_2020-01-14-2300", 
            "comp_baseline": "not-found", 
            "gpu_utests": [], 
            "material_budget_comparison": "not-found", 
            "merged_prs": [
                {
                    "hash": "510b5def2d58ae01c64d9b86cbe6be7ceaee83c9", 
                    "title": "CaloParticle additional hitsAndEnergies from SimClusters: data format change", 
                    "url": "https://github.com/cms-sw/cmssw/pull/28579", 
                    "number": "28579", 
                    "is_merge_commit": false, 
                    "from_merge_commit": false, 
                    "author_login": "bmarzocc"
                }, 
                {
                    "hash": "dbced6d05deaf8a4f2e22b43e6ba03de0873e1af", 
                    "title": "esConsumes migration, 4 more modules", 
                    "url": "https://github.com/cms-sw/cmssw/pull/28710", 
                    "number": "28710", 
                    "is_merge_commit": false, 
                    "from_merge_commit": false, 
                    "author_login": "wddgit"
                }, 
                {
                    "hash": "a8b6fa2f28a219f2b4f871b11609cd595d8832ec", 
                    "title": "Add CMS_SA_ALLOW before try statements where catch (...) is used to skip static analyzer warning.", 
                    "url": "https://github.com/cms-sw/cmssw/pull/28715", 
                    "number": "28715", 
                    "is_merge_commit": false, 
                    "from_merge_commit": false, 
                    "author_login": "gartung"
                }, 
                {
                    "hash": "709db16fb329d9f3283008c96a4b96a7c389c9e3", 
                    "title": "Fix muon track producer and muon hl tvalidation", 
                    "url": "https://github.com/cms-sw/cmssw/pull/28662", 
                    "number": "28662", 
                    "is_merge_commit": false, 
                    "from_merge_commit": false, 
                    "author_login": "abbiendi"
                }, 
                {
                    "hash": "9472f998d3777c164a8fced0e2e9c45d2b431057", 
                    "title": "DQM: New tests and Demo", 
                    "url": "https://github.com/cms-sw/cmssw/pull/28612", 
                    "number": "28612", 
                    "is_merge_commit": false, 
                    "from_merge_commit": false, 
                    "author_login": "schneiml"
                }, 
                {
                    "hash": "eb057df93e08fb0b3a3b7e5273ebc69219730adb", 
                    "title": "esConsumes migration DTChamberEfficiency", 
                    "url": "https://github.com/cms-sw/cmssw/pull/28730", 
                    "number": "28730", 
                    "is_merge_commit": false, 
                    "from_merge_commit": false, 
                    "author_login": "wddgit"
                }, 
                {
                    "hash": "4e7a960a139dc9654fd4b311a3a2e7a7935d2b28", 
                    "title": "Payload Inspector: add more two-tags comparisons", 
                    "url": "https://github.com/cms-sw/cmssw/pull/28725", 
                    "number": "28725", 
                    "is_merge_commit": false, 
                    "from_merge_commit": false, 
                    "author_login": "mmusich"
                }
            ], 
            "fwlite": [], 
            "invalid_includes": [], 
            "builds": [
                {
                    "arch": "slc7_amd64_gcc820", 
                    "passed": "passed", 
                    "file": "/data/sdt/buildlogs/slc7_amd64_gcc820/www/tue/11.1.ROOT6-tue-23/CMSSW_11_1_ROOT6_X_2020-01-14-2300/new/logAnalysis.pkl", 
                    "details": {
                        "ignoreWarning": 145
                    }
                }
            ], 
            "material_budget_v2": "not-found", 
            "static_checks_v2": "not-found", 
            "valgrind": "not-found", 
            "material_budget": "not-found", 
            "dupDict": [
                {
                    "arch": "slc7_amd64_gcc820", 
                    "passed": "passed"
                }
            ], 
            "static_checks_failures": "not-found", 
            "static_checks": "not-found", 
            "isIB": true, 
            "inProgress": false, 
            "addons": [], 
            "hlt_tests": "not-found"
        }, 
        {
            "comp_baseline_state": "errors", 
            "python3_tests": [], 
            "tests_archs": [
                "slc7_amd64_gcc820"
            ], 
            "cmsdist_merged_prs": {
                "slc7_amd64_gcc820": []
            }, 
            "cmsdist_compared_tags": {
                "slc7_amd64_gcc820": "IB/CMSSW_11_1_ROOT6_X_2020-01-12-2300/slc7_amd64_gcc820..IB/CMSSW_11_1_ROOT6_X_2020-01-12-2300/slc7_amd64_gcc820"
            }, 
            "cmsdistTags": {
                "slc7_amd64_gcc820": "IB/CMSSW_11_1_ROOT6_X_2020-01-12-2300/slc7_amd64_gcc820"
            }, 
            "next_ib": false, 
            "RVExceptions": null, 
            "igprof": "not-found", 
            "base_branch": "CMSSW_11_1_X", 
            "compared_tags": "CMSSW_11_1_ROOT6_X_2020-01-12-2300-->CMSSW_11_1_ROOT6_X_2020-01-13-2300", 
            "dqm_tests": "found", 
            "utests": [
                {
                    "arch": "slc7_amd64_gcc820", 
                    "passed": "passed", 
                    "file": "/data/sdt/buildlogs/slc7_amd64_gcc820/www/mon/11.1.ROOT6-mon-23/CMSSW_11_1_ROOT6_X_2020-01-13-2300/unitTests-summary.log", 
                    "details": {
                        "num_fails": "0"
                    }
                }
            ], 
            "ib_date": "2020-01-13-2300-0000", 
            "relvals": [
                {
                    "done": true, 
                    "arch": "slc7_amd64_gcc820", 
                    "passed": false, 
                    "file": "/data/sdt/buildlogs/slc7_amd64_gcc820/www/mon/11.1.ROOT6-mon-23/CMSSW_11_1_ROOT6_X_2020-01-13-2300/pyRelValMatrixLogs/run/runall-report-step123-.log", 
                    "details": {
                        "num_passed": 3164, 
                        "known_failed": 0, 
                        "num_failed": 1
                    }
                }
            ], 
            "release_queue": "CMSSW_11_1_ROOT6_X", 
            "release_name": "CMSSW_11_1_ROOT6_X_2020-01-13-2300", 
            "comp_baseline": "not-found", 
            "gpu_utests": [], 
            "material_budget_comparison": "not-found", 
            "merged_prs": [
                {
                    "hash": "b3259d5ce3ec70fe0e4d65fff181cd399566e768", 
                    "title": "DQM: new DQMFileSaver", 
                    "url": "https://github.com/cms-sw/cmssw/pull/28588", 
                    "number": "28588", 
                    "is_merge_commit": false, 
                    "from_merge_commit": false, 
                    "author_login": "schneiml"
                }, 
                {
                    "hash": "2df3ca12e4228f0c9b5bdfa02d9eb0a46f47bba5", 
                    "title": "Add ability to set RandomEngineStates in Service", 
                    "url": "https://github.com/cms-sw/cmssw/pull/28729", 
                    "number": "28729", 
                    "is_merge_commit": false, 
                    "from_merge_commit": false, 
                    "author_login": "Dr15Jones"
                }, 
                {
                    "hash": "685923d54487d8020558009840ca47065f1ec775", 
                    "title": "Move Sequence to Task Reconstruction_cff", 
                    "url": "https://github.com/cms-sw/cmssw/pull/28678", 
                    "number": "28678", 
                    "is_merge_commit": false, 
                    "from_merge_commit": false, 
                    "author_login": "jeongeun"
                }, 
                {
                    "hash": "6dfe29fa50e5c57b726f8654e94c7ec744d98d2c", 
                    "title": "Fixing HB thresholds E/gamma saved rec-hits for run3 ", 
                    "url": "https://github.com/cms-sw/cmssw/pull/28723", 
                    "number": "28723", 
                    "is_merge_commit": false, 
                    "from_merge_commit": false, 
                    "author_login": "Sam-Harper"
                }, 
                {
                    "hash": "5d29327b7921b3166143df7d9034897612fa55f3", 
                    "title": "HFNose: add 2D clusters", 
                    "url": "https://github.com/cms-sw/cmssw/pull/28468", 
                    "number": "28468", 
                    "is_merge_commit": false, 
                    "from_merge_commit": false, 
                    "author_login": "mariadalfonso"
                }, 
                {
                    "hash": "e4810f5fb7250ff2cce4eda4a653757e30a32b0e", 
                    "title": "ECAL for Time dependent MC. Premix option C. Handle for APD/PN tag for time dependence", 
                    "url": "https://github.com/cms-sw/cmssw/pull/28214", 
                    "number": "28214", 
                    "is_merge_commit": false, 
                    "from_merge_commit": false, 
                    "author_login": "amassiro"
                }, 
                {
                    "hash": "8c7259c6ab7cbb7e7a3092728e190ceefa325cf1", 
                    "title": "PPS: vector classes used in reco, geometry etc.", 
                    "url": "https://github.com/cms-sw/cmssw/pull/28726", 
                    "number": "28726", 
                    "is_merge_commit": false, 
                    "from_merge_commit": false, 
                    "author_login": "CTPPS"
                }, 
                {
                    "hash": "7fe8b377e4932807691f0c089ea4a62d9712eda4", 
                    "title": "Fix reading memory after freed in HLTPerformanceInfo", 
                    "url": "https://github.com/cms-sw/cmssw/pull/28727", 
                    "number": "28727", 
                    "is_merge_commit": false, 
                    "from_merge_commit": false, 
                    "author_login": "Dr15Jones"
                }
            ], 
            "fwlite": [], 
            "invalid_includes": [], 
            "builds": [
                {
                    "arch": "slc7_amd64_gcc820", 
                    "passed": "passed", 
                    "file": "/data/sdt/buildlogs/slc7_amd64_gcc820/www/mon/11.1.ROOT6-mon-23/CMSSW_11_1_ROOT6_X_2020-01-13-2300/new/logAnalysis.pkl", 
                    "details": {
                        "ignoreWarning": 20
                    }
                }
            ], 
            "material_budget_v2": "not-found", 
            "static_checks_v2": "not-found", 
            "valgrind": "not-found", 
            "material_budget": "not-found", 
            "dupDict": [
                {
                    "arch": "slc7_amd64_gcc820", 
                    "passed": "passed"
                }
            ], 
            "static_checks_failures": "not-found", 
            "static_checks": "not-found", 
            "isIB": true, 
            "inProgress": false, 
            "addons": [
                {
                    "arch": "slc7_amd64_gcc820", 
                    "passed": true, 
                    "file": "/data/sdt/buildlogs/slc7_amd64_gcc820/www/mon/11.1.ROOT6-mon-23/CMSSW_11_1_ROOT6_X_2020-01-13-2300/addOnTests.log", 
                    "details": {}
                }
            ], 
            "hlt_tests": "not-found"
        }, 
        {
            "comp_baseline_state": "errors", 
            "python3_tests": [], 
            "tests_archs": [
                "slc7_amd64_gcc820"
            ], 
            "cmsdist_merged_prs": {
                "slc7_amd64_gcc820": []
            }, 
            "cmsdist_compared_tags": {
                "slc7_amd64_gcc820": "IB/CMSSW_11_1_ROOT6_X_2020-01-12-2300/slc7_amd64_gcc820..IB/CMSSW_11_1_ROOT6_X_2020-01-12-2300/slc7_amd64_gcc820"
            }, 
            "cmsdistTags": {
                "slc7_amd64_gcc820": "IB/CMSSW_11_1_ROOT6_X_2020-01-12-2300/slc7_amd64_gcc820"
            }, 
            "next_ib": false, 
            "RVExceptions": null, 
            "igprof": "not-found", 
            "base_branch": "CMSSW_11_1_X", 
            "compared_tags": "CMSSW_11_1_ROOT6_X_2020-01-10-2300-->CMSSW_11_1_ROOT6_X_2020-01-12-2300", 
            "dqm_tests": "found", 
            "utests": [
                {
                    "arch": "slc7_amd64_gcc820", 
                    "passed": "passed", 
                    "file": "/data/sdt/buildlogs/slc7_amd64_gcc820/www/sun/11.1.ROOT6-sun-23/CMSSW_11_1_ROOT6_X_2020-01-12-2300/unitTests-summary.log", 
                    "details": {
                        "num_fails": "0"
                    }
                }
            ], 
            "ib_date": "2020-01-12-2300-0000", 
            "relvals": [
                {
                    "done": true, 
                    "arch": "slc7_amd64_gcc820", 
                    "passed": true, 
                    "file": "/data/sdt/buildlogs/slc7_amd64_gcc820/www/sun/11.1.ROOT6-sun-23/CMSSW_11_1_ROOT6_X_2020-01-12-2300/pyRelValMatrixLogs/run/runall-report-step123-.log", 
                    "details": {
                        "num_passed": 3150, 
                        "known_failed": 0, 
                        "num_failed": 0
                    }
                }
            ], 
            "release_queue": "CMSSW_11_1_ROOT6_X", 
            "release_name": "CMSSW_11_1_ROOT6_X_2020-01-12-2300", 
            "comp_baseline": "not-found", 
            "gpu_utests": [], 
            "material_budget_comparison": "not-found", 
            "merged_prs": [], 
            "fwlite": [], 
            "invalid_includes": [], 
            "builds": [
                {
                    "arch": "slc7_amd64_gcc820", 
                    "passed": "passed", 
                    "file": "/data/sdt/buildlogs/slc7_amd64_gcc820/www/sun/11.1.ROOT6-sun-23/CMSSW_11_1_ROOT6_X_2020-01-12-2300/new/logAnalysis.pkl", 
                    "details": {
                        "ignoreWarning": 144
                    }
                }
            ], 
            "material_budget_v2": "not-found", 
            "static_checks_v2": "not-found", 
            "valgrind": "not-found", 
            "material_budget": "not-found", 
            "dupDict": [
                {
                    "arch": "slc7_amd64_gcc820", 
                    "passed": "passed"
                }
            ], 
            "static_checks_failures": "not-found", 
            "static_checks": "not-found", 
            "isIB": true, 
            "inProgress": false, 
            "addons": [
                {
                    "arch": "slc7_amd64_gcc820", 
                    "passed": true, 
                    "file": "/data/sdt/buildlogs/slc7_amd64_gcc820/www/sun/11.1.ROOT6-sun-23/CMSSW_11_1_ROOT6_X_2020-01-12-2300/addOnTests.log", 
                    "details": {}
                }
            ], 
            "hlt_tests": "not-found"
        }, 
        {
            "comp_baseline_state": "errors", 
            "python3_tests": [], 
            "tests_archs": [], 
            "cmsdist_merged_prs": {}, 
            "cmsdist_compared_tags": {}, 
            "cmsdistTags": {
                "slc7_amd64_gcc820": "IB/CMSSW_11_1_ROOT6_X_2020-01-10-2300/slc7_amd64_gcc820"
            }, 
            "next_ib": false, 
            "RVExceptions": null, 
            "igprof": "not-found", 
            "base_branch": "CMSSW_11_1_X", 
            "compared_tags": "CMSSW_11_1_ROOT6_X_2020-01-10-1100-->CMSSW_11_1_ROOT6_X_2020-01-10-2300", 
            "dqm_tests": "found", 
            "utests": [], 
            "ib_date": "2020-01-10-2300-0000", 
            "relvals": [], 
            "release_queue": "CMSSW_11_1_ROOT6_X", 
            "release_name": "CMSSW_11_1_ROOT6_X_2020-01-10-2300", 
            "comp_baseline": "not-found", 
            "gpu_utests": [], 
            "material_budget_comparison": "not-found", 
            "merged_prs": [
                {
                    "hash": "ca5be563553a4722b4e36854f234f97c2a6430a5", 
                    "title": "Run3-hcx246 Small changes to the dd4hep codes", 
                    "url": "https://github.com/cms-sw/cmssw/pull/28700", 
                    "number": "28700", 
                    "is_merge_commit": false, 
                    "from_merge_commit": false, 
                    "author_login": "bsunanda"
                }, 
                {
                    "hash": "e8efbb29f49a0100d797295123ab8ab62da29f5c", 
                    "title": "EventSetup consumes migration, SiStrip modules", 
                    "url": "https://github.com/cms-sw/cmssw/pull/28683", 
                    "number": "28683", 
                    "is_merge_commit": false, 
                    "from_merge_commit": false, 
                    "author_login": "wddgit"
                }
            ], 
            "fwlite": [], 
            "invalid_includes": [], 
            "builds": [], 
            "material_budget_v2": "not-found", 
            "static_checks_v2": "not-found", 
            "valgrind": "not-found", 
            "material_budget": "not-found", 
            "dupDict": [], 
            "static_checks_failures": "not-found", 
            "static_checks": "not-found", 
            "isIB": true, 
            "inProgress": false, 
            "addons": [], 
            "hlt_tests": "not-found"
        }, 
        {
            "comp_baseline_state": "errors", 
            "python3_tests": [], 
            "tests_archs": [], 
            "cmsdist_merged_prs": {}, 
            "cmsdist_compared_tags": {}, 
            "cmsdistTags": {
                "slc7_amd64_gcc820": "IB/CMSSW_11_1_ROOT6_X_2020-01-10-1100/slc7_amd64_gcc820"
            }, 
            "next_ib": false, 
            "RVExceptions": null, 
            "igprof": "not-found", 
            "base_branch": "CMSSW_11_1_X", 
            "compared_tags": "CMSSW_11_1_ROOT6_X_2020-01-09-2300-->CMSSW_11_1_ROOT6_X_2020-01-10-1100", 
            "dqm_tests": "found", 
            "utests": [], 
            "ib_date": "2020-01-10-1100-0000", 
            "relvals": [], 
            "release_queue": "CMSSW_11_1_ROOT6_X", 
            "release_name": "CMSSW_11_1_ROOT6_X_2020-01-10-1100", 
            "comp_baseline": "not-found", 
            "gpu_utests": [], 
            "material_budget_comparison": "not-found", 
            "merged_prs": [
                {
                    "hash": "e275c63953516aa2368ca42e6059e0351d39543e", 
                    "title": "APE estimation tool: Enable submission of skims to condor, rearrange skimming tool, add phase 0 geometry support for plotting tools.", 
                    "url": "https://github.com/cms-sw/cmssw/pull/28638", 
                    "number": "28638", 
                    "is_merge_commit": false, 
                    "from_merge_commit": false, 
                    "author_login": "mteroerd"
                }, 
                {
                    "hash": "3f9bd0679367ac4d9c92e8ff1523d7b0aa203c00", 
                    "title": "Phase out old pre-GED GsfElectron sequence", 
                    "url": "https://github.com/cms-sw/cmssw/pull/28429", 
                    "number": "28429", 
                    "is_merge_commit": false, 
                    "from_merge_commit": false, 
                    "author_login": "guitargeek"
                }, 
                {
                    "hash": "91d5a7f0d7d10f5597d4c436ec6b4cc7a40c40ab", 
                    "title": "quark and gluons Py8EGun", 
                    "url": "https://github.com/cms-sw/cmssw/pull/28658", 
                    "number": "28658", 
                    "is_merge_commit": false, 
                    "from_merge_commit": false, 
                    "author_login": "vberta"
                }
            ], 
            "fwlite": [], 
            "invalid_includes": [], 
            "builds": [], 
            "material_budget_v2": "not-found", 
            "static_checks_v2": "not-found", 
            "valgrind": "not-found", 
            "material_budget": "not-found", 
            "dupDict": [], 
            "static_checks_failures": "not-found", 
            "static_checks": "not-found", 
            "isIB": true, 
            "inProgress": false, 
            "addons": [], 
            "hlt_tests": "not-found"
        }, 
        {
            "comp_baseline_state": "errors", 
            "python3_tests": [], 
            "tests_archs": [], 
            "cmsdist_merged_prs": {}, 
            "cmsdist_compared_tags": {}, 
            "cmsdistTags": {
                "slc7_amd64_gcc820": "IB/CMSSW_11_1_ROOT6_X_2020-01-09-2300/slc7_amd64_gcc820"
            }, 
            "next_ib": false, 
            "RVExceptions": null, 
            "igprof": "not-found", 
            "base_branch": "CMSSW_11_1_X", 
            "compared_tags": "CMSSW_11_1_ROOT6_X_2020-01-09-0800-->CMSSW_11_1_ROOT6_X_2020-01-09-2300", 
            "dqm_tests": "found", 
            "utests": [], 
            "ib_date": "2020-01-09-2300-0000", 
            "relvals": [], 
            "release_queue": "CMSSW_11_1_ROOT6_X", 
            "release_name": "CMSSW_11_1_ROOT6_X_2020-01-09-2300", 
            "comp_baseline": "not-found", 
            "gpu_utests": [], 
            "material_budget_comparison": "not-found", 
            "merged_prs": [
                {
                    "hash": "fc0d5e804b847118f2ad9af2dd8d6e6b2ff1c777", 
                    "title": "[DQMOffline/Trigger] added \"requireValidHLTPaths\" flag to plugins using GenericTriggerEventFlag", 
                    "url": "https://github.com/cms-sw/cmssw/pull/28627", 
                    "number": "28627", 
                    "is_merge_commit": false, 
                    "from_merge_commit": false, 
                    "author_login": "missirol"
                }, 
                {
                    "hash": "3845390f0bd1ee6dd890193ad55b253332d21d1b", 
                    "title": "Standardize include order in a few DataFormats packages", 
                    "url": "https://github.com/cms-sw/cmssw/pull/28717", 
                    "number": "28717", 
                    "is_merge_commit": false, 
                    "from_merge_commit": false, 
                    "author_login": "davidlange6"
                }, 
                {
                    "hash": "b986b6d114edf06fa96c79544441998d261e98d7", 
                    "title": "Changes to the PPS pixels Online/Offline DQM", 
                    "url": "https://github.com/cms-sw/cmssw/pull/28714", 
                    "number": "28714", 
                    "is_merge_commit": false, 
                    "from_merge_commit": false, 
                    "author_login": "AndreaBellora"
                }, 
                {
                    "hash": "a13cecf9e4312c20b135991b7d117e30fb29e1c4", 
                    "title": "EventSetup consumes migration, 4 DQM modules", 
                    "url": "https://github.com/cms-sw/cmssw/pull/28718", 
                    "number": "28718", 
                    "is_merge_commit": false, 
                    "from_merge_commit": false, 
                    "author_login": "wddgit"
                }, 
                {
                    "hash": "34341091495ed7c9fe6bc86e34f47392b1a88d84", 
                    "title": "Remove global declarations in classes.h in L1TNtuples", 
                    "url": "https://github.com/cms-sw/cmssw/pull/28692", 
                    "number": "28692", 
                    "is_merge_commit": false, 
                    "from_merge_commit": false, 
                    "author_login": "Dr15Jones"
                }, 
                {
                    "hash": "655e4dfa365589a64a6e6a2d5d7727f572a9a716", 
                    "title": "Remove global declarations in classes.h in L1THGCal", 
                    "url": "https://github.com/cms-sw/cmssw/pull/28693", 
                    "number": "28693", 
                    "is_merge_commit": false, 
                    "from_merge_commit": false, 
                    "author_login": "Dr15Jones"
                }, 
                {
                    "hash": "fa5d00adecf5d77370cca52ef396e03cf5a4ed28", 
                    "title": "DQM: Remove dqmEndRun in DQMEDAnalyzer", 
                    "url": "https://github.com/cms-sw/cmssw/pull/28552", 
                    "number": "28552", 
                    "is_merge_commit": false, 
                    "from_merge_commit": false, 
                    "author_login": "schneiml"
                }, 
                {
                    "hash": "860d65d064490030134838b5aef4d6fb581f8ebf", 
                    "title": "Removed non-const global from L1Trigger/L1TMuonOverlap", 
                    "url": "https://github.com/cms-sw/cmssw/pull/28696", 
                    "number": "28696", 
                    "is_merge_commit": false, 
                    "from_merge_commit": false, 
                    "author_login": "Dr15Jones"
                }, 
                {
                    "hash": "cabf76b31e0b815e78aee8b00e19e93717ec9b0a", 
                    "title": "Removed use of global histograms in DTVDriftCalibration", 
                    "url": "https://github.com/cms-sw/cmssw/pull/28697", 
                    "number": "28697", 
                    "is_merge_commit": false, 
                    "from_merge_commit": false, 
                    "author_login": "Dr15Jones"
                }, 
                {
                    "hash": "c20b045166de388291eb7baaa962929104593fed", 
                    "title": "Remove global declarations in classes.h in TrackTriggerAssociation", 
                    "url": "https://github.com/cms-sw/cmssw/pull/28694", 
                    "number": "28694", 
                    "is_merge_commit": false, 
                    "from_merge_commit": false, 
                    "author_login": "Dr15Jones"
                }, 
                {
                    "hash": "a814ee015ac91d7de734c55748b13b18e1f5d87f", 
                    "title": "Make classes.h in JetMETObjects conform to CondFormats conventions", 
                    "url": "https://github.com/cms-sw/cmssw/pull/28695", 
                    "number": "28695", 
                    "is_merge_commit": false, 
                    "from_merge_commit": false, 
                    "author_login": "Dr15Jones"
                }, 
                {
                    "hash": "a71992f3f5fc08e0a603b514b8b595be5c50f610", 
                    "title": "fix python includes for ALCARECOSiPixelCalCosmics to comply with Py3", 
                    "url": "https://github.com/cms-sw/cmssw/pull/28722", 
                    "number": "28722", 
                    "is_merge_commit": false, 
                    "from_merge_commit": false, 
                    "author_login": "mmusich"
                }, 
                {
                    "hash": "dbaace21503a00677e1e375e04e12b0c03f84070", 
                    "title": "Normalization removed for muon MC validation", 
                    "url": "https://github.com/cms-sw/cmssw/pull/28628", 
                    "number": "28628", 
                    "is_merge_commit": false, 
                    "from_merge_commit": false, 
                    "author_login": "cedricpri"
                }, 
                {
                    "hash": "2b979db78ad084db23c539db6a00b833610961f3", 
                    "title": "Avoid leaking memory in DTDeadFlagHandler", 
                    "url": "https://github.com/cms-sw/cmssw/pull/28698", 
                    "number": "28698", 
                    "is_merge_commit": false, 
                    "from_merge_commit": false, 
                    "author_login": "Dr15Jones"
                }, 
                {
                    "hash": "a98c6e0f9bcbed01524e205feb3caa1acce458fa", 
                    "title": "TestProcessor supports Run and Lumi product testing", 
                    "url": "https://github.com/cms-sw/cmssw/pull/28721", 
                    "number": "28721", 
                    "is_merge_commit": false, 
                    "from_merge_commit": false, 
                    "author_login": "Dr15Jones"
                }, 
                {
                    "hash": "738d45db89d01cf562929b762dcb7f72648e98f9", 
                    "title": "Properly handle file open for Streamer based sources", 
                    "url": "https://github.com/cms-sw/cmssw/pull/28666", 
                    "number": "28666", 
                    "is_merge_commit": false, 
                    "from_merge_commit": false, 
                    "author_login": "Dr15Jones"
                }
            ], 
            "fwlite": [], 
            "invalid_includes": [], 
            "builds": [], 
            "material_budget_v2": "not-found", 
            "static_checks_v2": "not-found", 
            "valgrind": "not-found", 
            "material_budget": "not-found", 
            "dupDict": [], 
            "static_checks_failures": "not-found", 
            "static_checks": "not-found", 
            "isIB": true, 
            "inProgress": false, 
            "addons": [], 
            "hlt_tests": "not-found"
        }, 
        {
            "comp_baseline_state": "errors", 
            "python3_tests": [], 
            "tests_archs": [], 
            "cmsdist_merged_prs": {}, 
            "cmsdist_compared_tags": {}, 
            "cmsdistTags": {
                "slc7_amd64_gcc820": "IB/CMSSW_11_1_ROOT6_X_2020-01-09-0800/slc7_amd64_gcc820"
            }, 
            "next_ib": false, 
            "RVExceptions": null, 
            "igprof": "not-found", 
            "base_branch": "CMSSW_11_1_X", 
            "compared_tags": "CMSSW_11_1_ROOT6_X_2020-01-08-2300-->CMSSW_11_1_ROOT6_X_2020-01-09-0800", 
            "dqm_tests": "inprogress", 
            "utests": [], 
            "ib_date": "2020-01-09-0800-0000", 
            "relvals": [], 
            "release_queue": "CMSSW_11_1_ROOT6_X", 
            "release_name": "CMSSW_11_1_ROOT6_X_2020-01-09-0800", 
            "comp_baseline": "not-found", 
            "gpu_utests": [], 
            "material_budget_comparison": "not-found", 
            "merged_prs": [], 
            "fwlite": [], 
            "invalid_includes": [], 
            "builds": [], 
            "material_budget_v2": "not-found", 
            "static_checks_v2": "not-found", 
            "valgrind": "not-found", 
            "material_budget": "not-found", 
            "dupDict": [], 
            "static_checks_failures": "not-found", 
            "static_checks": "not-found", 
            "isIB": true, 
            "inProgress": false, 
            "addons": [], 
            "hlt_tests": "not-found"
        }, 
        {
            "comp_baseline_state": "errors", 
            "python3_tests": [], 
            "tests_archs": [], 
            "cmsdist_merged_prs": {}, 
            "cmsdist_compared_tags": {}, 
            "cmsdistTags": {
                "slc7_amd64_gcc820": "ERR/CMSSW_11_1_ROOT6_X_2020-01-08-2300/slc7_amd64_gcc820"
            }, 
            "next_ib": false, 
            "RVExceptions": null, 
            "igprof": "not-found", 
            "base_branch": "CMSSW_11_1_X", 
            "compared_tags": "CMSSW_11_1_ROOT6_X_2020-01-07-2300-->CMSSW_11_1_ROOT6_X_2020-01-08-2300", 
            "dqm_tests": "inprogress", 
            "utests": [], 
            "ib_date": "2020-01-08-2300-0000", 
            "relvals": [], 
            "release_queue": "CMSSW_11_1_ROOT6_X", 
            "release_name": "CMSSW_11_1_ROOT6_X_2020-01-08-2300", 
            "comp_baseline": "not-found", 
            "gpu_utests": [], 
            "material_budget_comparison": "not-found", 
            "merged_prs": [
                {
                    "hash": "a1be73e85d0f404351b504aa2f0b0d194567cc94", 
                    "title": "Use correct beamspot for 2016 MC + update MC tracker alignment scenario for 2016 pre-VFP era", 
                    "url": "https://github.com/cms-sw/cmssw/pull/28624", 
                    "number": "28624", 
                    "is_merge_commit": false, 
                    "from_merge_commit": false, 
                    "author_login": "christopheralanwest"
                }, 
                {
                    "hash": "d2c9db7bd8a561dfc96267594fb0cc6a412af926", 
                    "title": "Run3-TB47 Test and validate TB simulation of HGCal", 
                    "url": "https://github.com/cms-sw/cmssw/pull/28705", 
                    "number": "28705", 
                    "is_merge_commit": false, 
                    "from_merge_commit": false, 
                    "author_login": "bsunanda"
                }, 
                {
                    "hash": "917af3f5541c8d1266b78b46c10791d36b542692", 
                    "title": "Test also ESGetToken in ESTestAnalyzers", 
                    "url": "https://github.com/cms-sw/cmssw/pull/28708", 
                    "number": "28708", 
                    "is_merge_commit": false, 
                    "from_merge_commit": false, 
                    "author_login": "makortel"
                }, 
                {
                    "hash": "1dd3a3d996196ec7ab5842620ff0a32969e56097", 
                    "title": "DQM: new DQMGlobalEDAnalyzer", 
                    "url": "https://github.com/cms-sw/cmssw/pull/28407", 
                    "number": "28407", 
                    "is_merge_commit": false, 
                    "from_merge_commit": false, 
                    "author_login": "schneiml"
                }, 
                {
                    "hash": "7ada40625d5aee49370b31d9ae6ebf10e5073cd1", 
                    "title": "Use PREMIX in the name of the .97 workflow", 
                    "url": "https://github.com/cms-sw/cmssw/pull/28470", 
                    "number": "28470", 
                    "is_merge_commit": false, 
                    "from_merge_commit": false, 
                    "author_login": "makortel"
                }, 
                {
                    "hash": "8d30421bea7a184b115317b5dcf3eb90e9867515", 
                    "title": "Run3-alca159 Study isolated track property", 
                    "url": "https://github.com/cms-sw/cmssw/pull/28685", 
                    "number": "28685", 
                    "is_merge_commit": false, 
                    "from_merge_commit": false, 
                    "author_login": "bsunanda"
                }, 
                {
                    "hash": "043fbdf6c0c5ab99c11dfa586fdadefc118b08c4", 
                    "title": "Introducing SiPixelCalSingleMuon ALCARECO", 
                    "url": "https://github.com/cms-sw/cmssw/pull/28535", 
                    "number": "28535", 
                    "is_merge_commit": false, 
                    "from_merge_commit": false, 
                    "author_login": "tvami"
                }
            ], 
            "fwlite": [], 
            "invalid_includes": [], 
            "builds": [], 
            "material_budget_v2": "not-found", 
            "static_checks_v2": "not-found", 
            "valgrind": "not-found", 
            "material_budget": "not-found", 
            "dupDict": [], 
            "static_checks_failures": "not-found", 
            "static_checks": "not-found", 
            "isIB": true, 
            "inProgress": false, 
            "addons": [], 
            "hlt_tests": "not-found"
        }, 
        {
            "comp_baseline_state": "errors", 
            "python3_tests": [], 
            "tests_archs": [], 
            "cmsdist_merged_prs": {}, 
            "cmsdist_compared_tags": {}, 
            "cmsdistTags": {}, 
            "next_ib": false, 
            "RVExceptions": null, 
            "igprof": "not-found", 
            "base_branch": "CMSSW_11_1_X", 
            "compared_tags": "CMSSW_11_1_ROOT6_X_2020-01-06-2300-->CMSSW_11_1_ROOT6_X_2020-01-07-2300", 
            "dqm_tests": "inprogress", 
            "utests": [], 
            "ib_date": "2020-01-07-2300-0000", 
            "relvals": [], 
            "release_queue": "CMSSW_11_1_ROOT6_X", 
            "release_name": "CMSSW_11_1_ROOT6_X_2020-01-07-2300", 
            "comp_baseline": "not-found", 
            "gpu_utests": [], 
            "material_budget_comparison": "not-found", 
            "merged_prs": [
                {
                    "hash": "2686d0a1d1bf9b0df3cac62543028710a669e484", 
                    "title": "Apply strict memory ownership to muon tracking", 
                    "url": "https://github.com/cms-sw/cmssw/pull/28701", 
                    "number": "28701", 
                    "is_merge_commit": false, 
                    "from_merge_commit": false, 
                    "author_login": "Dr15Jones"
                }, 
                {
                    "hash": "901cd2164db8f7f50e1715a4ccd9c2a9b9c2fbc7", 
                    "title": "Fix SwitchProducer unit test for python3", 
                    "url": "https://github.com/cms-sw/cmssw/pull/28702", 
                    "number": "28702", 
                    "is_merge_commit": false, 
                    "from_merge_commit": false, 
                    "author_login": "makortel"
                }, 
                {
                    "hash": "702cace81592305e13a56aada6e85b0c965c86f8", 
                    "title": "Return HitRZCompatibility and TrackingRegion by unique_ptr in TrackingRegion", 
                    "url": "https://github.com/cms-sw/cmssw/pull/28704", 
                    "number": "28704", 
                    "is_merge_commit": false, 
                    "from_merge_commit": false, 
                    "author_login": "makortel"
                }, 
                {
                    "hash": "bd2104708ad1e63ee7a2fd8eb32b874471ec454e", 
                    "title": "Add std::atomic_flag to exception list", 
                    "url": "https://github.com/cms-sw/cmssw/pull/28712", 
                    "number": "28712", 
                    "is_merge_commit": false, 
                    "from_merge_commit": false, 
                    "author_login": "gartung"
                }, 
                {
                    "hash": "25228df3b11d9f8f853ac856c0a3b63edb5b551c", 
                    "title": "Return ClusterParam by unique_ptr in PixelCPE", 
                    "url": "https://github.com/cms-sw/cmssw/pull/28706", 
                    "number": "28706", 
                    "is_merge_commit": false, 
                    "from_merge_commit": false, 
                    "author_login": "makortel"
                }, 
                {
                    "hash": "b494898c55dbd16ecbeb5791c3791d95291b3c6b", 
                    "title": "Remove global declarations in classes.h in CaloAnalysis", 
                    "url": "https://github.com/cms-sw/cmssw/pull/28691", 
                    "number": "28691", 
                    "is_merge_commit": false, 
                    "from_merge_commit": false, 
                    "author_login": "Dr15Jones"
                }, 
                {
                    "hash": "e49cab5e680bb9455f269fc541486be2b2cc066e", 
                    "title": "add mising resets for a couple of vectors in TrackingNtuple", 
                    "url": "https://github.com/cms-sw/cmssw/pull/28713", 
                    "number": "28713", 
                    "is_merge_commit": false, 
                    "from_merge_commit": false, 
                    "author_login": "slava77"
                }, 
                {
                    "hash": "e6b5b8a5eddff8cb53cbd3004bee3275f5747237", 
                    "title": "Remove dead assignments in Validation/RecoEgamma/plugins", 
                    "url": "https://github.com/cms-sw/cmssw/pull/28687", 
                    "number": "28687", 
                    "is_merge_commit": false, 
                    "from_merge_commit": false, 
                    "author_login": "perrotta"
                }, 
                {
                    "hash": "6c57594486c692d59d2249193cf5f344fce3e801", 
                    "title": "Correct MTDGeomDet type problems", 
                    "url": "https://github.com/cms-sw/cmssw/pull/28590", 
                    "number": "28590", 
                    "is_merge_commit": false, 
                    "from_merge_commit": false, 
                    "author_login": "dan131riley"
                }
            ], 
            "fwlite": [], 
            "invalid_includes": [], 
            "builds": [], 
            "material_budget_v2": "not-found", 
            "static_checks_v2": "not-found", 
            "valgrind": "not-found", 
            "material_budget": "not-found", 
            "dupDict": [], 
            "static_checks_failures": "not-found", 
            "static_checks": "not-found", 
            "isIB": true, 
            "inProgress": false, 
            "addons": [], 
            "hlt_tests": "not-found"
        }, 
        {
            "comp_baseline_state": "errors", 
            "python3_tests": [], 
            "tests_archs": [], 
            "cmsdist_merged_prs": {}, 
            "cmsdist_compared_tags": {}, 
            "cmsdistTags": {
                "slc7_amd64_gcc820": "IB/CMSSW_11_1_ROOT6_X_2020-01-06-2300/slc7_amd64_gcc820"
            }, 
            "next_ib": false, 
            "RVExceptions": null, 
            "igprof": "not-found", 
            "base_branch": "CMSSW_11_1_X", 
            "compared_tags": "CMSSW_11_1_ROOT6_X_2020-01-05-2300-->CMSSW_11_1_ROOT6_X_2020-01-06-2300", 
            "dqm_tests": "inprogress", 
            "utests": [], 
            "ib_date": "2020-01-06-2300-0000", 
            "relvals": [], 
            "release_queue": "CMSSW_11_1_ROOT6_X", 
            "release_name": "CMSSW_11_1_ROOT6_X_2020-01-06-2300", 
            "comp_baseline": "not-found", 
            "gpu_utests": [], 
            "material_budget_comparison": "not-found", 
            "merged_prs": [], 
            "fwlite": [], 
            "invalid_includes": [], 
            "builds": [], 
            "material_budget_v2": "not-found", 
            "static_checks_v2": "not-found", 
            "valgrind": "not-found", 
            "material_budget": "not-found", 
            "dupDict": [], 
            "static_checks_failures": "not-found", 
            "static_checks": "not-found", 
            "isIB": true, 
            "inProgress": false, 
            "addons": [], 
            "hlt_tests": "not-found"
        }, 
        {
            "comp_baseline_state": "errors", 
            "python3_tests": [], 
            "tests_archs": [], 
            "cmsdist_merged_prs": {}, 
            "cmsdist_compared_tags": {}, 
            "cmsdistTags": {
                "slc7_amd64_gcc820": "IB/CMSSW_11_1_ROOT6_X_2020-01-05-2300/slc7_amd64_gcc820"
            }, 
            "next_ib": false, 
            "RVExceptions": null, 
            "igprof": "not-found", 
            "base_branch": "CMSSW_11_1_X", 
            "compared_tags": "CMSSW_11_1_ROOT6_X_2020-01-05-0000-->CMSSW_11_1_ROOT6_X_2020-01-05-2300", 
            "dqm_tests": "inprogress", 
            "utests": [], 
            "ib_date": "2020-01-05-2300-0000", 
            "relvals": [], 
            "release_queue": "CMSSW_11_1_ROOT6_X", 
            "release_name": "CMSSW_11_1_ROOT6_X_2020-01-05-2300", 
            "comp_baseline": "not-found", 
            "gpu_utests": [], 
            "material_budget_comparison": "not-found", 
            "merged_prs": [], 
            "fwlite": [], 
            "invalid_includes": [], 
            "builds": [], 
            "material_budget_v2": "not-found", 
            "static_checks_v2": "not-found", 
            "valgrind": "not-found", 
            "material_budget": "not-found", 
            "dupDict": [], 
            "static_checks_failures": "not-found", 
            "static_checks": "not-found", 
            "isIB": true, 
            "inProgress": false, 
            "addons": [], 
            "hlt_tests": "not-found"
        }, 
        {
            "comp_baseline_state": "errors", 
            "python3_tests": [], 
            "tests_archs": [], 
            "cmsdist_merged_prs": {}, 
            "cmsdist_compared_tags": {}, 
            "cmsdistTags": {}, 
            "next_ib": false, 
            "RVExceptions": null, 
            "igprof": "not-found", 
            "base_branch": "CMSSW_11_1_X", 
            "compared_tags": "CMSSW_11_1_ROOT6_X_2020-01-05-0000-->CMSSW_11_1_ROOT6_X_2020-01-05-0000", 
            "dqm_tests": "inprogress", 
            "utests": [], 
            "ib_date": "2020-01-05-0000-0000", 
            "relvals": [], 
            "release_queue": "CMSSW_11_1_ROOT6_X", 
            "release_name": "CMSSW_11_1_ROOT6_X_2020-01-05-0000", 
            "comp_baseline": "not-found", 
            "gpu_utests": [], 
            "material_budget_comparison": "not-found", 
            "merged_prs": [], 
            "fwlite": [], 
            "invalid_includes": [], 
            "builds": [], 
            "material_budget_v2": "not-found", 
            "static_checks_v2": "not-found", 
            "valgrind": "not-found", 
            "material_budget": "not-found", 
            "dupDict": [], 
            "static_checks_failures": "not-found", 
            "static_checks": "not-found", 
            "isIB": true, 
            "inProgress": false, 
            "addons": [], 
            "hlt_tests": "not-found"
        }
    ]
}