{
  "avg": {
    "46": [
      "1020.0"
    ], 
    "53": [
      "2017.8"
    ], 
    "60": [
      "135.8"
    ], 
    "68": [
      "505.0"
    ], 
    "73": [
      "525.0", 
      "561.0"
    ], 
    "78": [
      "531.0"
    ], 
    "79": [
      "528.0", 
      "516.0", 
      "513.0", 
      "519.0", 
      "560.0", 
      "1010.0", 
      "506.0"
    ], 
    "81": [
      "510.0"
    ], 
    "90": [
      "545.0"
    ], 
    "91": [
      "102.0"
    ], 
    "97": [
      "521.0"
    ], 
    "107": [
      "250399.17"
    ], 
    "110": [
      "507.0"
    ], 
    "116": [
      "250399.0"
    ], 
    "117": [
      "508.0", 
      "136.7801"
    ], 
    "118": [
      "541.0"
    ], 
    "120": [
      "124.1"
    ], 
    "121": [
      "504.0"
    ], 
    "132": [
      "500199.0"
    ], 
    "139": [
      "124.2"
    ], 
    "143": [
      "136.7722"
    ], 
    "146": [
      "136.7802"
    ], 
    "149": [
      "503.0"
    ], 
    "151": [
      "551.0"
    ], 
    "153": [
      "123.2"
    ], 
    "154": [
      "523.0", 
      "101.0"
    ], 
    "160": [
      "123.1"
    ], 
    "161": [
      "124.5"
    ], 
    "162": [
      "514.0"
    ], 
    "166": [
      "509.0"
    ], 
    "168": [
      "124.6"
    ], 
    "172": [
      "250199.0"
    ], 
    "173": [
      "1325.6"
    ], 
    "182": [
      "5.3", 
      "134.813"
    ], 
    "184": [
      "556.0"
    ], 
    "187": [
      "250199.17"
    ], 
    "192": [
      "1329.1"
    ], 
    "193": [
      "5.5"
    ], 
    "195": [
      "135.13", 
      "5.2"
    ], 
    "199": [
      "5.7"
    ], 
    "201": [
      "5.4"
    ], 
    "203": [
      "124.4"
    ], 
    "204": [
      "123.3", 
      "2017.13"
    ], 
    "210": [
      "105.0", 
      "5.1"
    ], 
    "211": [
      "555.0"
    ], 
    "214": [
      "1308.0"
    ], 
    "220": [
      "5.6"
    ], 
    "225": [
      "136.8311"
    ], 
    "227": [
      "136.733"
    ], 
    "229": [
      "1325.1"
    ], 
    "240": [
      "1325.3"
    ], 
    "241": [
      "1325.7"
    ], 
    "249": [
      "140.51"
    ], 
    "255": [
      "4.22"
    ], 
    "256": [
      "1325.8"
    ], 
    "260": [
      "1307.0"
    ], 
    "262": [
      "140.54", 
      "562.0"
    ], 
    "266": [
      "534.0"
    ], 
    "272": [
      "1.0"
    ], 
    "275": [
      "150.3"
    ], 
    "277": [
      "517.0", 
      "1003.0"
    ], 
    "278": [
      "1325.51"
    ], 
    "283": [
      "135.2", 
      "135.3"
    ], 
    "287": [
      "150.1"
    ], 
    "289": [
      "135.7"
    ], 
    "290": [
      "527.0"
    ], 
    "291": [
      "2017.3", 
      "2017.5"
    ], 
    "293": [
      "250406.0"
    ], 
    "295": [
      "106.0", 
      "135.12"
    ], 
    "298": [
      "135.6", 
      "250400.0"
    ], 
    "300": [
      "135.9", 
      "2017.7", 
      "250400.17"
    ], 
    "301": [
      "524.0", 
      "250402.0", 
      "150.2"
    ], 
    "302": [
      "135.1"
    ], 
    "303": [
      "250409.0"
    ], 
    "304": [
      "2017.6", 
      "144.6"
    ], 
    "305": [
      "250408.0", 
      "530.0"
    ], 
    "307": [
      "135.4", 
      "135.11"
    ], 
    "313": [
      "135.5", 
      "250409.17"
    ], 
    "316": [
      "2017.2", 
      "250402.17"
    ], 
    "318": [
      "2017.9", 
      "2017.4"
    ], 
    "319": [
      "7.0", 
      "103.0"
    ], 
    "320": [
      "520.0"
    ], 
    "322": [
      "250408.17"
    ], 
    "325": [
      "10024.3"
    ], 
    "328": [
      "1002.0", 
      "250402.171"
    ], 
    "331": [
      "10024.1", 
      "2017.1"
    ], 
    "332": [
      "250405.0"
    ], 
    "335": [
      "130.0"
    ], 
    "336": [
      "1301.0"
    ], 
    "338": [
      "250406.17", 
      "250407.0"
    ], 
    "339": [
      "122.0"
    ], 
    "340": [
      "10024.5"
    ], 
    "342": [
      "127.0", 
      "250403.0", 
      "140.52"
    ], 
    "343": [
      "7.1", 
      "4.6"
    ], 
    "344": [
      "250407.17"
    ], 
    "347": [
      "552.0", 
      "128.0"
    ], 
    "348": [
      "2017.11"
    ], 
    "352": [
      "131.0"
    ], 
    "361": [
      "2017.12"
    ], 
    "362": [
      "512.0"
    ], 
    "363": [
      "126.0"
    ], 
    "366": [
      "4008.0"
    ], 
    "367": [
      "250403.17"
    ], 
    "368": [
      "129.0"
    ], 
    "372": [
      "120.0"
    ], 
    "375": [
      "1311.0"
    ], 
    "377": [
      "302.0"
    ], 
    "378": [
      "515.0", 
      "110.0"
    ], 
    "379": [
      "1317.0"
    ], 
    "381": [
      "300.0", 
      "554.0"
    ], 
    "385": [
      "25406.0"
    ], 
    "387": [
      "522.0"
    ], 
    "394": [
      "1315.0"
    ], 
    "395": [
      "1329.0"
    ], 
    "399": [
      "1322.0", 
      "134.0"
    ], 
    "400": [
      "1354.0"
    ], 
    "401": [
      "1321.0"
    ], 
    "403": [
      "1306.0"
    ], 
    "405": [
      "1348.0"
    ], 
    "410": [
      "1328.0", 
      "1327.0", 
      "1323.0"
    ], 
    "411": [
      "1332.0"
    ], 
    "412": [
      "1310.0"
    ], 
    "414": [
      "1351.0", 
      "1347.0"
    ], 
    "416": [
      "1355.0"
    ], 
    "418": [
      "1340.0", 
      "1325.2", 
      "1330.0"
    ], 
    "419": [
      "4.43"
    ], 
    "423": [
      "250405.17"
    ], 
    "424": [
      "1353.0"
    ], 
    "425": [
      "4001.0", 
      "1365.0", 
      "529.0"
    ], 
    "429": [
      "1325.4"
    ], 
    "431": [
      "136.7721"
    ], 
    "432": [
      "1314.0"
    ], 
    "434": [
      "136.735"
    ], 
    "438": [
      "1004.0"
    ], 
    "442": [
      "301.0", 
      "1336.0"
    ], 
    "448": [
      "134.911"
    ], 
    "455": [
      "136.7611"
    ], 
    "464": [
      "1325.5"
    ], 
    "488": [
      "518.0"
    ], 
    "493": [
      "526.0"
    ], 
    "590": [
      "1361.0"
    ], 
    "633": [
      "136.791"
    ], 
    "658": [
      "10024.6"
    ], 
    "669": [
      "10424.0"
    ], 
    "672": [
      "136.803"
    ], 
    "677": [
      "10009.0"
    ], 
    "678": [
      "10024.2"
    ], 
    "681": [
      "10004.0"
    ], 
    "682": [
      "1363.0"
    ], 
    "683": [
      "10024.4"
    ], 
    "692": [
      "10007.0"
    ], 
    "695": [
      "1362.0"
    ], 
    "698": [
      "10025.0"
    ], 
    "703": [
      "10023.0"
    ], 
    "715": [
      "10026.0"
    ], 
    "719": [
      "25210.0"
    ], 
    "720": [
      "10071.0"
    ], 
    "732": [
      "500203.0"
    ], 
    "733": [
      "10024.0"
    ], 
    "734": [
      "10006.0"
    ], 
    "738": [
      "10002.0"
    ], 
    "739": [
      "500206.0"
    ], 
    "740": [
      "500200.0"
    ], 
    "747": [
      "10042.0"
    ], 
    "751": [
      "10003.0", 
      "10005.0"
    ], 
    "752": [
      "10001.0"
    ], 
    "762": [
      "500207.0"
    ], 
    "764": [
      "500202.0"
    ], 
    "790": [
      "500204.0"
    ], 
    "797": [
      "10008.0"
    ], 
    "800": [
      "10059.0"
    ], 
    "803": [
      "25211.0"
    ], 
    "808": [
      "500205.0"
    ], 
    "816": [
      "11224.0"
    ], 
    "827": [
      "25213.0"
    ], 
    "833": [
      "10842.0"
    ], 
    "836": [
      "25212.0"
    ], 
    "847": [
      "11623.0"
    ], 
    "859": [
      "10823.0"
    ], 
    "869": [
      "11642.0"
    ], 
    "889": [
      "1361.17"
    ], 
    "891": [
      "10225.0"
    ], 
    "903": [
      "10824.0"
    ], 
    "913": [
      "11624.0"
    ], 
    "919": [
      "10224.0"
    ], 
    "933": [
      "11625.0"
    ], 
    "938": [
      "1363.17"
    ], 
    "950": [
      "1362.17"
    ], 
    "996": [
      "25211.17"
    ], 
    "1057": [
      "250206.0"
    ], 
    "1066": [
      "250203.0"
    ], 
    "1082": [
      "250202.0"
    ], 
    "1097": [
      "250204.0"
    ], 
    "1103": [
      "250200.0"
    ], 
    "1109": [
      "250207.0"
    ], 
    "1120": [
      "25212.17"
    ], 
    "1124": [
      "25213.17"
    ], 
    "1127": [
      "250205.0"
    ], 
    "1351": [
      "148.0"
    ], 
    "1463": [
      "250207.17"
    ], 
    "1479": [
      "250205.17"
    ], 
    "1493": [
      "250204.17"
    ], 
    "1494": [
      "250203.17"
    ], 
    "1495": [
      "250200.17"
    ], 
    "1529": [
      "250206.17"
    ], 
    "1538": [
      "250202.17"
    ], 
    "1698": [
      "250208.17"
    ]
  }, 
  "workflows": {
    "1.0": [
      272
    ], 
    "10001.0": [
      752
    ], 
    "10002.0": [
      738
    ], 
    "10003.0": [
      751
    ], 
    "10004.0": [
      681
    ], 
    "10005.0": [
      751
    ], 
    "10006.0": [
      734
    ], 
    "10007.0": [
      692
    ], 
    "10008.0": [
      797
    ], 
    "10009.0": [
      677
    ], 
    "1002.0": [
      328
    ], 
    "10023.0": [
      703
    ], 
    "10024.0": [
      733
    ], 
    "10024.1": [
      331
    ], 
    "10024.2": [
      678
    ], 
    "10024.3": [
      325
    ], 
    "10024.4": [
      683
    ], 
    "10024.5": [
      340
    ], 
    "10024.6": [
      658
    ], 
    "10025.0": [
      698
    ], 
    "10026.0": [
      715
    ], 
    "1003.0": [
      277
    ], 
    "1004.0": [
      438
    ], 
    "10042.0": [
      747
    ], 
    "10059.0": [
      800
    ], 
    "10071.0": [
      720
    ], 
    "101.0": [
      154
    ], 
    "1010.0": [
      79
    ], 
    "102.0": [
      91
    ], 
    "1020.0": [
      46
    ], 
    "10224.0": [
      919
    ], 
    "10225.0": [
      891
    ], 
    "103.0": [
      319
    ], 
    "10424.0": [
      669
    ], 
    "105.0": [
      210
    ], 
    "106.0": [
      295
    ], 
    "10823.0": [
      859
    ], 
    "10824.0": [
      903
    ], 
    "10842.0": [
      833
    ], 
    "110.0": [
      378
    ], 
    "11224.0": [
      816
    ], 
    "11623.0": [
      847
    ], 
    "11624.0": [
      913
    ], 
    "11625.0": [
      933
    ], 
    "11642.0": [
      869
    ], 
    "120.0": [
      372
    ], 
    "122.0": [
      339
    ], 
    "123.1": [
      160
    ], 
    "123.2": [
      153
    ], 
    "123.3": [
      204
    ], 
    "124.1": [
      120
    ], 
    "124.2": [
      139
    ], 
    "124.4": [
      203
    ], 
    "124.5": [
      161
    ], 
    "124.6": [
      168
    ], 
    "126.0": [
      363
    ], 
    "127.0": [
      342
    ], 
    "128.0": [
      347
    ], 
    "129.0": [
      368
    ], 
    "130.0": [
      335
    ], 
    "1301.0": [
      336
    ], 
    "1306.0": [
      403
    ], 
    "1307.0": [
      260
    ], 
    "1308.0": [
      214
    ], 
    "131.0": [
      352
    ], 
    "1310.0": [
      412
    ], 
    "1311.0": [
      375
    ], 
    "1314.0": [
      432
    ], 
    "1315.0": [
      394
    ], 
    "1317.0": [
      379
    ], 
    "1321.0": [
      401
    ], 
    "1322.0": [
      399
    ], 
    "1323.0": [
      410
    ], 
    "1325.1": [
      229
    ], 
    "1325.2": [
      418
    ], 
    "1325.3": [
      240
    ], 
    "1325.4": [
      429
    ], 
    "1325.5": [
      464
    ], 
    "1325.51": [
      278
    ], 
    "1325.6": [
      173
    ], 
    "1325.7": [
      241
    ], 
    "1325.8": [
      256
    ], 
    "1327.0": [
      410
    ], 
    "1328.0": [
      410
    ], 
    "1329.0": [
      395
    ], 
    "1329.1": [
      192
    ], 
    "1330.0": [
      418
    ], 
    "1332.0": [
      411
    ], 
    "1336.0": [
      442
    ], 
    "134.0": [
      399
    ], 
    "134.813": [
      182
    ], 
    "134.911": [
      448
    ], 
    "1340.0": [
      418
    ], 
    "1347.0": [
      414
    ], 
    "1348.0": [
      405
    ], 
    "135.1": [
      302
    ], 
    "135.11": [
      307
    ], 
    "135.12": [
      295
    ], 
    "135.13": [
      195
    ], 
    "135.2": [
      283
    ], 
    "135.3": [
      283
    ], 
    "135.4": [
      307
    ], 
    "135.5": [
      313
    ], 
    "135.6": [
      298
    ], 
    "135.7": [
      289
    ], 
    "135.8": [
      60
    ], 
    "135.9": [
      300
    ], 
    "1351.0": [
      414
    ], 
    "1353.0": [
      424
    ], 
    "1354.0": [
      400
    ], 
    "1355.0": [
      416
    ], 
    "136.733": [
      227
    ], 
    "136.735": [
      434
    ], 
    "136.7611": [
      455
    ], 
    "136.7721": [
      431
    ], 
    "136.7722": [
      143
    ], 
    "136.7801": [
      117
    ], 
    "136.7802": [
      146
    ], 
    "136.791": [
      633
    ], 
    "136.803": [
      672
    ], 
    "136.8311": [
      225
    ], 
    "1361.0": [
      590
    ], 
    "1361.17": [
      889
    ], 
    "1362.0": [
      695
    ], 
    "1362.17": [
      950
    ], 
    "1363.0": [
      682
    ], 
    "1363.17": [
      938
    ], 
    "1365.0": [
      425
    ], 
    "140.51": [
      249
    ], 
    "140.52": [
      342
    ], 
    "140.54": [
      262
    ], 
    "144.6": [
      304
    ], 
    "148.0": [
      1351
    ], 
    "150.1": [
      287
    ], 
    "150.2": [
      301
    ], 
    "150.3": [
      275
    ], 
    "2017.1": [
      331
    ], 
    "2017.11": [
      348
    ], 
    "2017.12": [
      361
    ], 
    "2017.13": [
      204
    ], 
    "2017.2": [
      316
    ], 
    "2017.3": [
      291
    ], 
    "2017.4": [
      318
    ], 
    "2017.5": [
      291
    ], 
    "2017.6": [
      304
    ], 
    "2017.7": [
      300
    ], 
    "2017.8": [
      53
    ], 
    "2017.9": [
      318
    ], 
    "250199.0": [
      172
    ], 
    "250199.17": [
      187
    ], 
    "250200.0": [
      1103
    ], 
    "250200.17": [
      1495
    ], 
    "250202.0": [
      1082
    ], 
    "250202.17": [
      1538
    ], 
    "250203.0": [
      1066
    ], 
    "250203.17": [
      1494
    ], 
    "250204.0": [
      1097
    ], 
    "250204.17": [
      1493
    ], 
    "250205.0": [
      1127
    ], 
    "250205.17": [
      1479
    ], 
    "250206.0": [
      1057
    ], 
    "250206.17": [
      1529
    ], 
    "250207.0": [
      1109
    ], 
    "250207.17": [
      1463
    ], 
    "250208.17": [
      1698
    ], 
    "250399.0": [
      116
    ], 
    "250399.17": [
      107
    ], 
    "250400.0": [
      298
    ], 
    "250400.17": [
      300
    ], 
    "250402.0": [
      301
    ], 
    "250402.17": [
      316
    ], 
    "250402.171": [
      328
    ], 
    "250403.0": [
      342
    ], 
    "250403.17": [
      367
    ], 
    "250405.0": [
      332
    ], 
    "250405.17": [
      423
    ], 
    "250406.0": [
      293
    ], 
    "250406.17": [
      338
    ], 
    "250407.0": [
      338
    ], 
    "250407.17": [
      344
    ], 
    "250408.0": [
      305
    ], 
    "250408.17": [
      322
    ], 
    "250409.0": [
      303
    ], 
    "250409.17": [
      313
    ], 
    "25210.0": [
      719
    ], 
    "25211.0": [
      803
    ], 
    "25211.17": [
      996
    ], 
    "25212.0": [
      836
    ], 
    "25212.17": [
      1120
    ], 
    "25213.0": [
      827
    ], 
    "25213.17": [
      1124
    ], 
    "25406.0": [
      385
    ], 
    "300.0": [
      381
    ], 
    "301.0": [
      442
    ], 
    "302.0": [
      377
    ], 
    "4.22": [
      255
    ], 
    "4.43": [
      419
    ], 
    "4.6": [
      343
    ], 
    "4001.0": [
      425
    ], 
    "4008.0": [
      366
    ], 
    "5.1": [
      210
    ], 
    "5.2": [
      195
    ], 
    "5.3": [
      182
    ], 
    "5.4": [
      201
    ], 
    "5.5": [
      193
    ], 
    "5.6": [
      220
    ], 
    "5.7": [
      199
    ], 
    "500199.0": [
      132
    ], 
    "500200.0": [
      740
    ], 
    "500202.0": [
      764
    ], 
    "500203.0": [
      732
    ], 
    "500204.0": [
      790
    ], 
    "500205.0": [
      808
    ], 
    "500206.0": [
      739
    ], 
    "500207.0": [
      762
    ], 
    "503.0": [
      149
    ], 
    "504.0": [
      121
    ], 
    "505.0": [
      68
    ], 
    "506.0": [
      79
    ], 
    "507.0": [
      110
    ], 
    "508.0": [
      117
    ], 
    "509.0": [
      166
    ], 
    "510.0": [
      81
    ], 
    "512.0": [
      362
    ], 
    "513.0": [
      79
    ], 
    "514.0": [
      162
    ], 
    "515.0": [
      378
    ], 
    "516.0": [
      79
    ], 
    "517.0": [
      277
    ], 
    "518.0": [
      488
    ], 
    "519.0": [
      79
    ], 
    "520.0": [
      320
    ], 
    "521.0": [
      97
    ], 
    "522.0": [
      387
    ], 
    "523.0": [
      154
    ], 
    "524.0": [
      301
    ], 
    "525.0": [
      73
    ], 
    "526.0": [
      493
    ], 
    "527.0": [
      290
    ], 
    "528.0": [
      79
    ], 
    "529.0": [
      425
    ], 
    "530.0": [
      305
    ], 
    "531.0": [
      78
    ], 
    "534.0": [
      266
    ], 
    "541.0": [
      118
    ], 
    "545.0": [
      90
    ], 
    "551.0": [
      151
    ], 
    "552.0": [
      347
    ], 
    "554.0": [
      381
    ], 
    "555.0": [
      211
    ], 
    "556.0": [
      184
    ], 
    "560.0": [
      79
    ], 
    "561.0": [
      73
    ], 
    "562.0": [
      262
    ], 
    "7.0": [
      319
    ], 
    "7.1": [
      343
    ]
  }
}
